calculator/__main__.py
calculator/calculator.py
my_calculator_app-0.1.1.dist-info/LICENSE
my_calculator_app-0.1.1.dist-info/METADATA
my_calculator_app-0.1.1.dist-info/WHEEL
my_calculator_app-0.1.1.dist-info/top_level.txt
my_calculator_app-0.1.1.dist-info/RECORD
