Metadata-Version: 2.1
Name: my-calculator-app
Version: 0.1.1
Summary: A simple calculator app for learning CI/CD and packaging.
Author-email: Susanne Jandl <susanne.jandl@edu.fh-joanneum.com>
License: MIT
Classifier: Programming Language :: Python :: 3
Classifier: License :: OSI Approved :: MIT License
Classifier: Operating System :: OS Independent
Requires-Python: >=3.7
License-File: LICENSE
Provides-Extra: dev
Requires-Dist: pytest; extra == "dev"
